<?xml version='1.0' encoding='UTF-8'?>

<bag>
 <fileEntry key="4186920366475949351" value="0"/>
 <fileEntry key="4186920424343472680" value="1"/>
 <fileEntry key="4186920482558366023" value="2"/>
 <fileEntry key="4186920544177888181" value="3"/>
 <fileEntry key="4186920614535280917" value="4"/>
 <fileEntry key="4186920675243342418" value="5"/>
 <fileEntry key="4186920734222741240" value="6"/>
 <fileEntry key="4186920792222350785" value="7"/>
 <fileEntry key="4186920849458343999" value="8"/>
 <fileEntry key="4186920907772702318" value="9"/>
 <fileEntry key="4186920965855212316" value="10"/>
</bag>
